{
  "timestamp": "2025-06-08T04:27:43.396368",
  "overall_status": "PASS",
  "tests": {
    "core_simulation_removal": {
      "status": "PASS",
      "issues_count": 0,
      "issues": []
    },
    "strategy_scoring_system": {
      "status": "PASS",
      "issues_count": 0,
      "issues": []
    },
    "key_functions": {
      "status": "PASS",
      "issues_count": 0,
      "issues": [],
      "quality_checks": [
        "run_all_strategy_simulations 已改为真实数据评估",
        "_get_real_price_history 已改为真实API调用"
      ]
    }
  },
  "summary": {
    "total_tests": 3,
    "passed_tests": 3,
    "pass_rate": 1.0
  }
}